{
  "structure": "individual",
  "payload": {
    "6s6ywfF3aJCdYpQdL": {
      "data": {
        "questions": ["<p>&nbsp;Ton nom est :&nbsp;</p>"],
        "answers": [null],
        "answersIndex": [-1],
        "maxCorrect": 1,
        "coordinates": {"x": 0, "y": 0},
        "form": {"0": {"text": "Sahar"}}
      }
    },
    "BasbmZQMvwwLAgtSM": {
      "data": {
        "questions": ["<p>&nbsp;Ton nom est :&nbsp;</p>"],
        "answers": [null],
        "answersIndex": [-1],
        "maxCorrect": 1,
        "coordinates": {"x": 0, "y": 0},
        "form": {"0": {"text": "Louis"}}
      }
    },
    "Bcei9rADYFhbKCp93": {
      "data": {
        "questions": ["<p>&nbsp;Ton nom est :&nbsp;</p>"],
        "answers": [null],
        "answersIndex": [-1],
        "maxCorrect": 1,
        "coordinates": {"x": 0, "y": 0},
        "form": {"0": {"text": "Nicolas"}}
      }
    },
    "Dz9wHmEWxcQubmTwW": {
      "data": {
        "questions": ["<p>&nbsp;Ton nom est :&nbsp;</p>"],
        "answers": [null],
        "answersIndex": [-1],
        "maxCorrect": 1,
        "coordinates": {"x": 0, "y": 0},
        "form": {"0": {"text": "Lisa"}}
      }
    },
    "KCwKjQb76cPjzx8JX": {
      "data": {
        "questions": ["<p>&nbsp;Ton nom est :&nbsp;</p>"],
        "answers": [null],
        "answersIndex": [-1],
        "maxCorrect": 1,
        "coordinates": {"x": 0, "y": 0},
        "form": {"0": {"text": "sonia"}}
      }
    },
    "MJq483N8WXHz9MzBk": {
      "data": {
        "questions": ["<p>&nbsp;Ton nom est :&nbsp;</p>"],
        "answers": [null],
        "answersIndex": [-1],
        "maxCorrect": 1,
        "coordinates": {"x": 0, "y": 0},
        "form": {"0": {"text": "Sébastien"}}
      }
    },
    "PireZZS4EC2YtDzr7": {
      "data": {
        "questions": ["<p>&nbsp;Ton nom est :&nbsp;</p>"],
        "answers": [null],
        "answersIndex": [-1],
        "maxCorrect": 1,
        "coordinates": {"x": 0, "y": 0},
        "form": {"0": {"text": "Emma"}}
      }
    },
    "WefycwLQ4YnmyXxbe": {
      "data": {
        "questions": ["<p>&nbsp;Ton nom est :&nbsp;</p>"],
        "answers": [null],
        "answersIndex": [-1],
        "maxCorrect": 1,
        "coordinates": {"x": 0, "y": 0},
        "form": {"0": {"text": "Marie \n\n"}}
      }
    },
    "a2Ckwzfe9yionRt8j": {
      "data": {
        "questions": ["<p>&nbsp;Ton nom est :&nbsp;</p>"],
        "answers": [null],
        "answersIndex": [-1],
        "maxCorrect": 1,
        "coordinates": {"x": 0, "y": 0},
        "form": {"0": {"text": "Alicia\n"}}
      }
    },
    "iFpwFjqWgCo8c2tRA": {
      "data": {
        "questions": ["<p>&nbsp;Ton nom est :&nbsp;</p>"],
        "answers": [null],
        "answersIndex": [-1],
        "maxCorrect": 1,
        "coordinates": {"x": 0, "y": 0},
        "form": {"0": {"text": "Antoine "}}
      }
    },
    "mL9jSJPubEFdL2hsZ": {
      "data": {
        "questions": ["<p>&nbsp;Ton nom est :&nbsp;</p>"],
        "answers": [null],
        "answersIndex": [-1],
        "maxCorrect": 1,
        "coordinates": {"x": 0, "y": 0},
        "form": {"0": {"text": "Léa"}}
      }
    },
    "oXAFHcyBLZPrTwCX5": {
      "data": {
        "questions": ["<p>&nbsp;Ton nom est :&nbsp;</p>"],
        "answers": [null],
        "answersIndex": [-1],
        "maxCorrect": 1,
        "coordinates": {"x": 0, "y": 0},
        "form": {"0": {"text": "paula"}}
      }
    },
    "qaQte2MipgdEF5ZTb": {
      "data": {
        "questions": ["<p>&nbsp;Ton nom est :&nbsp;</p>"],
        "answers": [null],
        "answersIndex": [-1],
        "maxCorrect": 1,
        "coordinates": {"x": 0, "y": 0},
        "form": {"0": {"text": "helio\n"}}
      }
    },
    "rgCgM5NdbNyergz9D": {
      "data": {
        "questions": ["<p>&nbsp;Ton nom est :&nbsp;</p>"],
        "answers": [null],
        "answersIndex": [-1],
        "maxCorrect": 1,
        "coordinates": {"x": 0, "y": 0},
        "form": {"0": {"text": "malik\n"}}
      }
    },
    "wBypYSiPx2wm2qK4S": {
      "data": {
        "questions": ["<p>&nbsp;Ton nom est :&nbsp;</p>"],
        "answers": [null],
        "answersIndex": [-1],
        "maxCorrect": 1,
        "coordinates": {"x": 0, "y": 0},
        "form": {"0": {"text": "Capucine"}}
      }
    },
    "xRSfbze8oF7h9QvFa": {
      "data": {
        "questions": ["<p>&nbsp;Ton nom est :&nbsp;</p>"],
        "answers": [null],
        "answersIndex": [-1],
        "maxCorrect": 1,
        "coordinates": {"x": 0, "y": 0},
        "form": {"0": {"text": "Henoch"}}
      }
    }
  }
}